FreeHugChat/__init__.py
FreeHugChat/chatbot.py
FreeHugChat-0.0.13.dist-info/LICENSE
FreeHugChat-0.0.13.dist-info/METADATA
FreeHugChat-0.0.13.dist-info/WHEEL
FreeHugChat-0.0.13.dist-info/top_level.txt
FreeHugChat-0.0.13.dist-info/RECORD
