Metadata-Version: 2.1
Name: FreeHugChat
Version: 0.0.13
Summary: an easy interface to interact with a chatbot
Author: RPNerd
Keywords: python,chatbot
Classifier: Development Status :: 1 - Planning
Classifier: Intended Audience :: Developers
Classifier: Programming Language :: Python :: 3
Classifier: Operating System :: Unix
Classifier: Operating System :: MacOS :: MacOS X
Classifier: Operating System :: Microsoft :: Windows
License-File: LICENSE
Requires-Dist: hugchat ==0.2.6
